eofs/__init__.py
eofs/_version.py
eofs/iris.py
eofs/standard.py
eofs/xarray.py
eofs/examples/__init__.py
eofs/examples/example_data/hgt_djf.nc
eofs/examples/example_data/sst_ndjfm_anom.nc
eofs/multivariate/__init__.py
eofs/multivariate/iris.py
eofs/multivariate/standard.py
eofs/tests/__init__.py
eofs/tests/reference.py
eofs/tests/test_error_handling.py
eofs/tests/test_multivariate_error_handling.py
eofs/tests/test_multivariate_solution.py
eofs/tests/test_solution.py
eofs/tests/test_tools.py
eofs/tests/utils.py
eofs/tests/data/eigenvalues.area.npy
eofs/tests/data/eigenvalues.area_multi.npy
eofs/tests/data/eigenvalues.area_multi_mix.npy
eofs/tests/data/eigenvalues.equal.npy
eofs/tests/data/eigenvalues.latitude.npy
eofs/tests/data/eofs.area.npy
eofs/tests/data/eofs.area_multi.npy
eofs/tests/data/eofs.area_multi_mix.npy
eofs/tests/data/eofs.equal.npy
eofs/tests/data/eofs.latitude.npy
eofs/tests/data/eofscor.area.npy
eofs/tests/data/eofscor.area_multi.npy
eofs/tests/data/eofscor.area_multi_mix.npy
eofs/tests/data/eofscor.equal.npy
eofs/tests/data/eofscor.latitude.npy
eofs/tests/data/eofscov.area.npy
eofs/tests/data/eofscov.area_multi.npy
eofs/tests/data/eofscov.area_multi_mix.npy
eofs/tests/data/eofscov.equal.npy
eofs/tests/data/eofscov.latitude.npy
eofs/tests/data/errors.area.npy
eofs/tests/data/errors.area_multi.npy
eofs/tests/data/errors.area_multi_mix.npy
eofs/tests/data/errors.equal.npy
eofs/tests/data/errors.latitude.npy
eofs/tests/data/latitude.npy
eofs/tests/data/longitude.npy
eofs/tests/data/pcs.area.npy
eofs/tests/data/pcs.area_multi.npy
eofs/tests/data/pcs.area_multi_mix.npy
eofs/tests/data/pcs.equal.npy
eofs/tests/data/pcs.latitude.npy
eofs/tests/data/rcon.area.npy
eofs/tests/data/rcon.area_multi.npy
eofs/tests/data/rcon.area_multi_mix.npy
eofs/tests/data/rcon.equal.npy
eofs/tests/data/rcon.latitude.npy
eofs/tests/data/scaled_errors.area.npy
eofs/tests/data/scaled_errors.area_multi.npy
eofs/tests/data/scaled_errors.area_multi_mix.npy
eofs-2.0.0.dist-info/COPYING
eofs-2.0.0.dist-info/METADATA
eofs-2.0.0.dist-info/WHEEL
eofs-2.0.0.dist-info/top_level.txt
eofs-2.0.0.dist-info/RECORD
