Metadata-Version: 2.1
Name: eofs
Version: 2.0.0
Summary: EOF analysis in Python
Author-email: Andrew Dawson <dawson@atm.ox.ac.uk>
License: GPL-3.0
Project-URL: documentation, https://ajdawson.github.io/eofs
Project-URL: homepage, https://github.com/ajdawson/eofs
Project-URL: repository, https://github.com/ajdawson/eofs
Classifier: Programming Language :: Python :: 3 :: Only
Classifier: Programming Language :: Python :: 3.8
Classifier: Programming Language :: Python :: 3.9
Classifier: Programming Language :: Python :: 3.10
Classifier: Programming Language :: Python :: 3.11
Classifier: Programming Language :: Python :: 3.12
Classifier: Programming Language :: Python :: 3.13
Requires-Python: >=3.8
License-File: COPYING
Requires-Dist: numpy
Provides-Extra: iris
Requires-Dist: scitools-iris; extra == "iris"
Provides-Extra: xarray
Requires-Dist: xarray; extra == "xarray"
